openconvert/__init__.py
openconvert/cli.py
openconvert/converter.py
openconvert/launcher.py
openconvert/converters/__init__.py
openconvert/converters/archive_converter.py
openconvert/converters/audio_converter.py
openconvert/converters/code_converter.py
openconvert/converters/document_converter.py
openconvert/converters/image_converter.py
openconvert/converters/model_converter.py
openconvert/converters/video_converter.py
openconvert-0.1.0.dist-info/METADATA
openconvert-0.1.0.dist-info/WHEEL
openconvert-0.1.0.dist-info/entry_points.txt
openconvert-0.1.0.dist-info/top_level.txt
openconvert-0.1.0.dist-info/RECORD
