Metadata-Version: 2.4
Name: openconvert
Version: 0.1.0
Summary: A versatile file and data conversion library
Home-page: https://github.com/openconvert/openconvert
Author: OpenConvert Team
Author-email: info@openconvert.org
Classifier: Programming Language :: Python :: 3
Classifier: License :: OSI Approved :: MIT License
Classifier: Operating System :: OS Independent
Requires-Python: >=3.7
Requires-Dist: pillow
Requires-Dist: reportlab
Requires-Dist: python-docx
Requires-Dist: PyPDF2
Requires-Dist: pandas
Requires-Dist: pyyaml
Requires-Dist: dicttoxml
Requires-Dist: xmltodict
Requires-Dist: markdown
Requires-Dist: beautifulsoup4
Requires-Dist: html2text
Provides-Extra: image
Requires-Dist: cairosvg; extra == "image"
Provides-Extra: audio
Requires-Dist: pydub; extra == "audio"
Requires-Dist: SpeechRecognition; extra == "audio"
Provides-Extra: video
Requires-Dist: moviepy; extra == "video"
Provides-Extra: document
Requires-Dist: pdf2image; extra == "document"
Provides-Extra: archive
Requires-Dist: py7zr; extra == "archive"
Requires-Dist: rarfile; extra == "archive"
Provides-Extra: model
Requires-Dist: trimesh; extra == "model"
Requires-Dist: numpy; extra == "model"
Requires-Dist: scipy; extra == "model"
Provides-Extra: all
Requires-Dist: cairosvg; extra == "all"
Requires-Dist: pydub; extra == "all"
Requires-Dist: SpeechRecognition; extra == "all"
Requires-Dist: moviepy; extra == "all"
Requires-Dist: pdf2image; extra == "all"
Requires-Dist: py7zr; extra == "all"
Requires-Dist: rarfile; extra == "all"
Requires-Dist: trimesh; extra == "all"
Requires-Dist: numpy; extra == "all"
Requires-Dist: scipy; extra == "all"
Dynamic: author
Dynamic: author-email
Dynamic: classifier
Dynamic: description
Dynamic: description-content-type
Dynamic: home-page
Dynamic: provides-extra
Dynamic: requires-dist
Dynamic: requires-python
Dynamic: summary
